nlic/__init__.py
nlic-0.0.0.dist-info/METADATA
nlic-0.0.0.dist-info/WHEEL
nlic-0.0.0.dist-info/top_level.txt
nlic-0.0.0.dist-info/RECORD
