Metadata-Version: 2.2
Name: nlic
Version: 0.0.0
Summary: Coming soon
Author-email: Jamesb <experimentallearning0@gmail.com>
